flucoma_torch/__init__.py
flucoma_torch/data.py
flucoma_torch/model.py
flucoma_torch/optimize_classifier.py
flucoma_torch/optimize_regressor.py
flucoma_torch/scaler.py
flucoma_torch/task.py
flucoma_torch/train_classifier.py
flucoma_torch/train_regressor.py
flucoma_torch/config/__init__.py
flucoma_torch/config/model.py
flucoma_torch/config/scaler.py
flucoma_torch-0.1.4.dist-info/METADATA
flucoma_torch-0.1.4.dist-info/WHEEL
flucoma_torch-0.1.4.dist-info/entry_points.txt
flucoma_torch-0.1.4.dist-info/RECORD
