Metadata-Version: 2.4
Name: flucoma-torch
Version: 0.1.4
Summary: Add your description here
Requires-Python: >=3.9
Requires-Dist: catalogue
Requires-Dist: hydra-core>=1.3
Requires-Dist: lightning>=2.0
Requires-Dist: loguru
Requires-Dist: optuna-integration[pytorch-lightning]
Requires-Dist: optuna>=4.0.0
Requires-Dist: torch>=2.0.0
Requires-Dist: torchaudio
